pycount_aa44/__init__.py
pycount_aa44/plotting_aa44.py
pycount_aa44/pycount_aa44.py
pycount_aa44-0.1.0.dist-info/LICENSE
pycount_aa44-0.1.0.dist-info/METADATA
pycount_aa44-0.1.0.dist-info/WHEEL
pycount_aa44-0.1.0.dist-info/RECORD
